fastargsnap/__init__.py
fastargsnap/cli.py
fastargsnap/core.py
fastargsnap-0.1.0.dist-info/licenses/LICENSE
fastargsnap-0.1.0.dist-info/METADATA
fastargsnap-0.1.0.dist-info/WHEEL
fastargsnap-0.1.0.dist-info/entry_points.txt
fastargsnap-0.1.0.dist-info/top_level.txt
fastargsnap-0.1.0.dist-info/RECORD
