Metadata-Version: 2.4
Name: fastargsnap
Version: 0.1.0
Summary: Fast argument completion using snapshot-based approach
Author-email: Uday Ayya <uday.ayya@gmail.com>
License-Expression: MIT
Project-URL: Homepage, https://github.com/udayayya/fastargsnap
Project-URL: Repository, https://github.com/udayayya/fastargsnap
Project-URL: Issues, https://github.com/udayayya/fastargsnap/issues
Keywords: cli,argparse,tab-completion,performance,snapshot,fast-completion
Classifier: Development Status :: 3 - Alpha
Classifier: Intended Audience :: Developers
Classifier: Programming Language :: Python :: 3
Classifier: Programming Language :: Python :: 3.8
Classifier: Programming Language :: Python :: 3.9
Classifier: Programming Language :: Python :: 3.10
Classifier: Programming Language :: Python :: 3.11
Classifier: Programming Language :: Python :: 3.12
Classifier: Topic :: Software Development :: Libraries :: Python Modules
Classifier: Topic :: System :: Shells
Classifier: Topic :: Utilities
Requires-Python: >=3.8
License-File: LICENSE
Requires-Dist: argparse
Requires-Dist: argcomplete
Provides-Extra: dev
Requires-Dist: pytest; extra == "dev"
Requires-Dist: black; extra == "dev"
Requires-Dist: flake8; extra == "dev"
Dynamic: license-file
